AUTHORS
MANIFEST.in
setup.py
django_naremitimg.egg-info/PKG-INFO
django_naremitimg.egg-info/SOURCES.txt
django_naremitimg.egg-info/dependency_links.txt
django_naremitimg.egg-info/not-zip-safe
django_naremitimg.egg-info/top_level.txt
naremitimg/__init__.py
naremitimg/naremitimg.py
naremitimg/views.py