Metadata-Version: 1.1
Name: django-naremitimg
Version: 0.1.2
Summary: A tiny Django app for performing image manipulations on the fly.
Home-page: https://github.com/naremit/NaremitIMG
Author: Jon Combe
Author-email: pypi@joncombe.net
License: BSD licence, see LICENCE file
Platform: UNKNOWN
Classifier: Development Status :: 4 - Beta
Classifier: Environment :: Web Environment
Classifier: Framework :: Django
Classifier: Intended Audience :: Developers
Classifier: License :: OSI Approved :: BSD License
Classifier: Natural Language :: English
Classifier: Programming Language :: Python
Classifier: Topic :: Multimedia :: Graphics
